imaplib3/__init__.py
imaplib3/base.py
imaplib3/exc.py
imaplib3/response.py
imaplib3/test_imaplib2.py
imaplib3-0.0.1.dist-info/DESCRIPTION.rst
imaplib3-0.0.1.dist-info/METADATA
imaplib3-0.0.1.dist-info/metadata.json
imaplib3-0.0.1.dist-info/RECORD
imaplib3-0.0.1.dist-info/top_level.txt
imaplib3-0.0.1.dist-info/WHEEL
