Metadata-Version: 2.0
Name: imaplib3
Version: 0.0.1
Summary: Python IMAP Library
Home-page: https://github.com/clara-labs/imaplib3
Author: Clara
Author-email: UNKNOWN
License: MIT
Keywords: imaplib,imap
Platform: UNKNOWN
Classifier: Development Status :: 4 - Beta
Classifier: Intended Audience :: Developers
Classifier: License :: OSI Approved :: MIT License
Classifier: Operating System :: OS Independent
Classifier: Programming Language :: Python
Classifier: Programming Language :: Python :: 2.5
Classifier: Programming Language :: Python :: 2.6
Classifier: Programming Language :: Python :: 2.7
Classifier: Topic :: Communications :: Email :: Post-Office :: IMAP
Classifier: Topic :: Software Development :: Libraries :: Python Modules
